apq.cpython-37m-x86_64-linux-gnu.so
apq-0.10.0.dist-info/RECORD
apq-0.10.0.dist-info/WHEEL
apq-0.10.0.dist-info/LICENSE
apq-0.10.0.dist-info/METADATA
apq-0.10.0.dist-info/top_level.txt
apq/_version.py
apq/__init__.pyi
apq/py.typed
